aibotweb/__init__.py
aibotweb/aibotweb.py
aibotweb-1.0.dist-info/LICENSE
aibotweb-1.0.dist-info/METADATA
aibotweb-1.0.dist-info/WHEEL
aibotweb-1.0.dist-info/top_level.txt
aibotweb-1.0.dist-info/RECORD
